factorial_nguyen/__init__.py
factorial_nguyen/app.py
factorial_nguyen/factorial.py
factorial_nguyen-0.1.0.dist-info/METADATA
factorial_nguyen-0.1.0.dist-info/WHEEL
factorial_nguyen-0.1.0.dist-info/RECORD
